{
  "_comment": "Scan allowlist for pptx skill. Documentation references only.",
  "allowlist": [
    {
      "file": "SKILL.md",
      "rules": ["HOME_PATH_REFERENCE"],
      "reason": "Documentation: ~/Documents/GroundPA Toolkit Workplace/output/ is the standard output path for generated files."
    },
    {
      "file": "references/workspace-setup.md",
      "rules": ["HOME_PATH_REFERENCE"],
      "reason": "Documentation: ~/Documents/GroundPA Toolkit Workplace/pptx/ is the standard workspace location."
    }
  ]
}
